mediaws/__init__.py
mediaws/imaple.py
mediaws/mediaws.py
mediaws/tmdbws.py
mediaws/videoinfo.py
mediaws/wikiws.py
mediaws_genwch-0.0.13.dist-info/LICENSE
mediaws_genwch-0.0.13.dist-info/METADATA
mediaws_genwch-0.0.13.dist-info/WHEEL
mediaws_genwch-0.0.13.dist-info/top_level.txt
mediaws_genwch-0.0.13.dist-info/RECORD
