Metadata-Version: 2.1
Name: mediaws-genwch
Version: 0.0.13
Summary: UNKNOWN
Home-page: https://gitlab.com/genwch/mediaws
Author: genwch
Author-email: 
License: UNKNOWN
Platform: UNKNOWN
Classifier: Programming Language :: Python :: 3
Classifier: License :: OSI Approved :: MIT License
Classifier: Operating System :: OS Independent
Requires-Python: >=3.7
License-File: LICENSE
Requires-Dist: requests
